nls/__init__.py
nls/core.py
nls/exception.py
nls/logging.py
nls/speech_recognizer.py
nls/speech_synthesizer.py
nls/speech_transcriber.py
nls/token.py
nls/util.py
nls/version.py
nls/websocket/__init__.py
nls/websocket/_abnf.py
nls/websocket/_app.py
nls/websocket/_cookiejar.py
nls/websocket/_core.py
nls/websocket/_exceptions.py
nls/websocket/_handshake.py
nls/websocket/_http.py
nls/websocket/_logging.py
nls/websocket/_socket.py
nls/websocket/_ssl_compat.py
nls/websocket/_url.py
nls/websocket/_utils.py
aliyun_nls-0.0.1.dist-info/LICENSE
aliyun_nls-0.0.1.dist-info/METADATA
aliyun_nls-0.0.1.dist-info/WHEEL
aliyun_nls-0.0.1.dist-info/top_level.txt
aliyun_nls-0.0.1.dist-info/RECORD
