Metadata-Version: 2.1
Name: aliyun-nls
Version: 0.0.1
Summary: aliyun-nls
Home-page: https://github.com/..
Author: jiaqi.sjq
Author-email: aliyun <aliyun@aliyun.com>
License: Apache License 2.0
Project-URL: Homepage, https://github.com/aliyun/alibabacloud-nls-python-sdk
Project-URL: Bug Tracker, https://github.com/aliyun/alibabacloud-nls-python-sdk/issues
Keywords: nls,sdk
Classifier: Programming Language :: Python :: 3
Classifier: License :: OSI Approved :: MIT License
Classifier: Operating System :: OS Independent
Requires-Python: >=3.6
License-File: LICENSE
Requires-Dist: oss2
Requires-Dist: aliyun-python-sdk-core (>=2.13.3)
Requires-Dist: matplotlib (>=3.3.4)
